Metadata-Version: 2.1
Name: NexaWatch
Version: 0.1
Summary: A nodemon alternative for Python
Home-page: https://github.com/yourusername/pywatcher
Author: Andrew Wade
Author-email: awade75009@gmail.com
License: UNKNOWN
Platform: UNKNOWN
